clustering.py
elements.py
main.py
pca.py
pymol.py
xyz.py
Parsing_Conformational_Families_OMOLAB-0.0.1.dist-info/METADATA
Parsing_Conformational_Families_OMOLAB-0.0.1.dist-info/WHEEL
Parsing_Conformational_Families_OMOLAB-0.0.1.dist-info/top_level.txt
Parsing_Conformational_Families_OMOLAB-0.0.1.dist-info/RECORD
