Metadata-Version: 2.1
Name: Parsing-Conformational-Families-OMOLAB
Version: 0.0.1
Summary: Uses PCA and K-means clustering to separate conformational ensembles. (xyz-files only)
Home-page: https://github.com/mattnw1/Conformational_Analysis
Author: Matthew Nwerem
Author-email: nwere100@mail.chapman.edu
License: UNKNOWN
Platform: UNKNOWN
Classifier: Programming Language :: Python :: 3
Classifier: Programming Language :: Python :: 2
Classifier: Development Status :: 4 - Beta
Classifier: Environment :: MacOS X
Classifier: Framework :: Matplotlib
Classifier: Intended Audience :: Education
Classifier: Intended Audience :: Science/Research
Classifier: License :: Free For Educational Use
Classifier: License :: Free For Home Use
Classifier: License :: Free for non-commercial use
Classifier: License :: OSI Approved :: MIT License
Classifier: Natural Language :: English
Classifier: Operating System :: MacOS
Classifier: Operating System :: Microsoft :: Windows
Classifier: Topic :: Scientific/Engineering :: Chemistry
Classifier: Topic :: Scientific/Engineering :: Information Analysis
